stikb/__init__.py
stikb-0.1.0.dist-info/METADATA
stikb-0.1.0.dist-info/WHEEL
stikb-0.1.0.dist-info/RECORD
