Metadata-Version: 2.1
Name: stikb
Version: 0.1.0
Summary: 
License: MIT
Author: Johannes Roos
Author-email: jhnnsrs@gmail.com
Requires-Python: >3.8
Classifier: License :: OSI Approved :: MIT License
Classifier: Programming Language :: Python :: 3
Classifier: Programming Language :: Python :: 3.9
Classifier: Programming Language :: Python :: 3.10
Classifier: Programming Language :: Python :: 3.11
Classifier: Programming Language :: Python :: 3.12
Requires-Dist: pydantic (<2)
